ForSEplus/__init__.py
ForSEplus/after_training_12amin.py
ForSEplus/after_training_3amin.py
ForSEplus/check_model.py
ForSEplus/forse_plus.py
ForSEplus/my_forse_class.py
ForSEplus/nn_tools.py
ForSEplus/projection_tools.py
ForSEplus/recompose_class.py
ForSEplus/test_import.py
ForSEplus/utility.py
ForSEplus/validation_class.py
ForSEplus-1.0.0rc0.dist-info/LICENSE
ForSEplus-1.0.0rc0.dist-info/METADATA
ForSEplus-1.0.0rc0.dist-info/WHEEL
ForSEplus-1.0.0rc0.dist-info/top_level.txt
ForSEplus-1.0.0rc0.dist-info/RECORD
