Metadata-Version: 2.1
Name: ForSEplus
Version: 1.0.0rc0
Summary: My package description
Author-email: Jian Yao <jyao@sissa.it>
License: MIT License
Project-URL: Homepage, https://github.com/yaojian95/ForSEplus
Keywords: feed,reader,tutorial
Classifier: License :: OSI Approved :: MIT License
Classifier: Programming Language :: Python
Classifier: Programming Language :: Python :: 3
License-File: LICENSE
